forku/__init__.py
forku/__main__.py
forku-0.0.2.dist-info/LICENSE.txt
forku-0.0.2.dist-info/METADATA
forku-0.0.2.dist-info/WHEEL
forku-0.0.2.dist-info/top_level.txt
forku-0.0.2.dist-info/RECORD
