Metadata-Version: 2.1
Name: forku
Version: 0.0.2
Summary: Forks a library you have patched...
Home-page: https://github.com/byteface/forku
Author: @byteface
Author-email: byteface@gmail.com
License: MIT
Download-URL: https://github.com/byteface/forku/archive/0.0.2 .tar.gz
Keywords: fork,patch
Platform: UNKNOWN
Classifier: Programming Language :: Python :: 3
Classifier: Programming Language :: Python
Classifier: Programming Language :: Python :: 3.6
Classifier: Programming Language :: Python :: 3.7
Classifier: Programming Language :: Python :: 3.8
Classifier: Programming Language :: Python :: 3.9
Classifier: Programming Language :: Python :: 3.10
Classifier: Development Status :: 4 - Beta
Classifier: Intended Audience :: Developers
Classifier: Intended Audience :: Other Audience
Classifier: License :: OSI Approved :: MIT License
Classifier: Topic :: Software Development
Classifier: Topic :: Terminals
Classifier: Topic :: Utilities
Classifier: Topic :: Software Development :: Libraries :: Python Modules
Requires-Python: >=3.6
